deepthought_ai/__init__.py
deepthought_ai/main.py
deepthought_ai_engine-0.1.2.dist-info/LICENSE.txt
deepthought_ai_engine-0.1.2.dist-info/METADATA
deepthought_ai_engine-0.1.2.dist-info/WHEEL
deepthought_ai_engine-0.1.2.dist-info/top_level.txt
deepthought_ai_engine-0.1.2.dist-info/RECORD
